{"mean":{"confidence_interval":{"confidence_level":0.95,"lower_bound":18904040.380083323,"upper_bound":18938713.695166666},"point_estimate":18921735.036666658,"standard_error":8835.685192356324},"median":{"confidence_interval":{"confidence_level":0.95,"lower_bound":18915971.833333336,"upper_bound":18962774.0},"point_estimate":18938123.0,"standard_error":12324.626192145333},"median_abs_dev":{"confidence_interval":{"confidence_level":0.95,"lower_bound":64694.732451444426,"upper_bound":111225.63842535204},"point_estimate":88244.35043334961,"standard_error":12319.411003120116},"slope":null,"std_dev":{"confidence_interval":{"confidence_level":0.95,"lower_bound":73738.64140714244,"upper_bound":103179.08160917723},"point_estimate":88911.41611463862,"standard_error":7524.88508108437}}