{"mean":{"confidence_interval":{"confidence_level":0.95,"lower_bound":18215245.009999994,"upper_bound":18225357.378166664},"point_estimate":18219888.903333332,"standard_error":2580.851341504329},"median":{"confidence_interval":{"confidence_level":0.95,"lower_bound":18209275.333333332,"upper_bound":18211408.666666668},"point_estimate":18209958.666666664,"standard_error":581.770260871039},"median_abs_dev":{"confidence_interval":{"confidence_level":0.95,"lower_bound":2643.722853066378,"upper_bound":5781.892797349043},"point_estimate":3953.599929805888,"standard_error":824.5475216494544},"slope":null,"std_dev":{"confidence_interval":{"confidence_level":0.95,"lower_bound":15571.420793553494,"upper_bound":34500.99058968451},"point_estimate":25869.082873643532,"standard_error":4810.732049233414}}