{"mean":{"confidence_interval":{"confidence_level":0.95,"lower_bound":98704.21818684788,"upper_bound":99281.43564171522},"point_estimate":98981.07930164051,"standard_error":147.57076895986694},"median":{"confidence_interval":{"confidence_level":0.95,"lower_bound":98186.28152225802,"upper_bound":99207.0},"point_estimate":98508.87727272727,"standard_error":236.8976249834795},"median_abs_dev":{"confidence_interval":{"confidence_level":0.95,"lower_bound":920.078188140039,"upper_bound":1820.4990636134205},"point_estimate":1309.733413956882,"standard_error":220.4415726570015},"slope":{"confidence_interval":{"confidence_level":0.95,"lower_bound":98062.14720369122,"upper_bound":98477.27484513001},"point_estimate":98254.6351726516,"standard_error":106.30763092914269},"std_dev":{"confidence_interval":{"confidence_level":0.95,"lower_bound":1151.1982055842316,"upper_bound":1895.8807532914539},"point_estimate":1486.915624093728,"standard_error":207.30710459435647}}