{"mean":{"confidence_interval":{"confidence_level":0.95,"lower_bound":10041358.4239,"upper_bound":10200497.426599998},"point_estimate":10119128.658,"standard_error":40683.80846324885},"median":{"confidence_interval":{"confidence_level":0.95,"lower_bound":9979163.4,"upper_bound":10159163.6},"point_estimate":10047753.5,"standard_error":43241.36545185222},"median_abs_dev":{"confidence_interval":{"confidence_level":0.95,"lower_bound":319676.27523811074,"upper_bound":473705.96237003774},"point_estimate":397841.0251969094,"standard_error":39479.77546066339},"slope":null,"std_dev":{"confidence_interval":{"confidence_level":0.95,"lower_bound":333101.9461798362,"upper_bound":481213.42379378545},"point_estimate":410245.00938157085,"standard_error":37919.030809343385}}