{"mean":{"confidence_interval":{"confidence_level":0.95,"lower_bound":10055603.5984,"upper_bound":10094809.4327},"point_estimate":10074859.922000002,"standard_error":10027.061521649975},"median":{"confidence_interval":{"confidence_level":0.95,"lower_bound":10046390.5,"upper_bound":10106370.2},"point_estimate":10063130.4,"standard_error":16878.740208246734},"median_abs_dev":{"confidence_interval":{"confidence_level":0.95,"lower_bound":65426.6920584443,"upper_bound":146243.7244141532},"point_estimate":93388.37930202429,"standard_error":20151.968807688772},"slope":null,"std_dev":{"confidence_interval":{"confidence_level":0.95,"lower_bound":86840.85780265614,"upper_bound":112717.81335584624},"point_estimate":100457.9578618399,"standard_error":6638.240720377161}}