{"mean":{"confidence_interval":{"confidence_level":0.95,"lower_bound":39519315.452125,"upper_bound":39669252.35525},"point_estimate":39595229.185,"standard_error":38378.1339752229},"median":{"confidence_interval":{"confidence_level":0.95,"lower_bound":39419306.5,"upper_bound":39878559.75},"point_estimate":39582711.5,"standard_error":166046.79404299898},"median_abs_dev":{"confidence_interval":{"confidence_level":0.95,"lower_bound":198341.48317873478,"upper_bound":656050.1177027822},"point_estimate":442971.5907856822,"standard_error":115406.76326351604},"slope":null,"std_dev":{"confidence_interval":{"confidence_level":0.95,"lower_bound":333389.1215294522,"upper_bound":428394.92546941823},"point_estimate":384417.0677687945,"standard_error":24267.28226185719}}