{"mean":{"confidence_interval":{"confidence_level":0.95,"lower_bound":509816.8351694736,"upper_bound":510135.5206962739},"point_estimate":509979.0893745502,"standard_error":81.42640801897882},"median":{"confidence_interval":{"confidence_level":0.95,"lower_bound":509827.93876262626,"upper_bound":510109.53466183576},"point_estimate":509950.5648351648,"standard_error":72.86287863642617},"median_abs_dev":{"confidence_interval":{"confidence_level":0.95,"lower_bound":374.50635159973234,"upper_bound":605.251393232355},"point_estimate":488.46749596434506,"standard_error":60.3351997654599},"slope":{"confidence_interval":{"confidence_level":0.95,"lower_bound":509859.4312879214,"upper_bound":510050.49766308157},"point_estimate":509956.7494783508,"standard_error":48.62888288523083},"std_dev":{"confidence_interval":{"confidence_level":0.95,"lower_bound":549.8189178739456,"upper_bound":1079.056049526168},"point_estimate":818.9200746617262,"standard_error":137.12285222409702}}