{"mean":{"confidence_interval":{"confidence_level":0.95,"lower_bound":52830.28307722911,"upper_bound":53037.66895742356},"point_estimate":52925.36906083766,"standard_error":53.11345220193393},"median":{"confidence_interval":{"confidence_level":0.95,"lower_bound":52765.43158327461,"upper_bound":52832.35220125786},"point_estimate":52804.596395502645,"standard_error":13.840195423224477},"median_abs_dev":{"confidence_interval":{"confidence_level":0.95,"lower_bound":98.02904210990498,"upper_bound":187.1517705708086},"point_estimate":136.3145827539125,"standard_error":22.03547142076219},"slope":{"confidence_interval":{"confidence_level":0.95,"lower_bound":52814.2577660155,"upper_bound":52907.193831116216},"point_estimate":52856.116986683744,"standard_error":23.9655987551895},"std_dev":{"confidence_interval":{"confidence_level":0.95,"lower_bound":319.3369848991377,"upper_bound":706.2809528538643},"point_estimate":534.2847503206297,"standard_error":98.54934422640316}}