{"mean":{"confidence_interval":{"confidence_level":0.95,"lower_bound":52749.32765406583,"upper_bound":52979.549154832},"point_estimate":52850.58573680294,"standard_error":59.22963856982062},"median":{"confidence_interval":{"confidence_level":0.95,"lower_bound":52686.576848370925,"upper_bound":52735.51106770833},"point_estimate":52704.348414179105,"standard_error":13.903246703297219},"median_abs_dev":{"confidence_interval":{"confidence_level":0.95,"lower_bound":93.88248886517141,"upper_bound":171.54386722103325},"point_estimate":114.35304371902531,"standard_error":21.719529136585447},"slope":{"confidence_interval":{"confidence_level":0.95,"lower_bound":52804.67456455957,"upper_bound":53135.036025377085},"point_estimate":52940.63042042264,"standard_error":86.16785255666444},"std_dev":{"confidence_interval":{"confidence_level":0.95,"lower_bound":250.16833188074963,"upper_bound":883.170214190143},"point_estimate":595.5006417002548,"standard_error":164.59717615751305}}