{"mean":{"confidence_interval":{"confidence_level":0.95,"lower_bound":52779.62349970678,"upper_bound":52977.93703077364},"point_estimate":52863.5303857343,"standard_error":51.0954867961449},"median":{"confidence_interval":{"confidence_level":0.95,"lower_bound":52750.41111111111,"upper_bound":52808.33924349882},"point_estimate":52782.35515873016,"standard_error":14.41090522131002},"median_abs_dev":{"confidence_interval":{"confidence_level":0.95,"lower_bound":107.73019017494913,"upper_bound":231.3797170113318},"point_estimate":172.01683157572617,"standard_error":31.533385980607534},"slope":{"confidence_interval":{"confidence_level":0.95,"lower_bound":52847.31583043187,"upper_bound":53193.161439749274},"point_estimate":52981.98393445315,"standard_error":92.07860477984761},"std_dev":{"confidence_interval":{"confidence_level":0.95,"lower_bound":227.03843227576345,"upper_bound":796.834032587195},"point_estimate":512.5376720419221,"standard_error":176.26347501413886}}