{"mean":{"confidence_interval":{"confidence_level":0.95,"lower_bound":9366.591928895332,"upper_bound":9777.036928862826},"point_estimate":9545.735882524557,"standard_error":105.51827678144859},"median":{"confidence_interval":{"confidence_level":0.95,"lower_bound":9273.410714285714,"upper_bound":9414.801041666668},"point_estimate":9364.452097039473,"standard_error":42.06394550872925},"median_abs_dev":{"confidence_interval":{"confidence_level":0.95,"lower_bound":136.4592176057731,"upper_bound":215.93723342223996},"point_estimate":179.50465973736317,"standard_error":19.559887510226993},"slope":{"confidence_interval":{"confidence_level":0.95,"lower_bound":9303.99856642297,"upper_bound":9981.591463449959},"point_estimate":9597.768830722625,"standard_error":172.96525084823932},"std_dev":{"confidence_interval":{"confidence_level":0.95,"lower_bound":263.8297922338408,"upper_bound":1569.105847122937},"point_estimate":1057.855864361767,"standard_error":317.79167838790625}}