{"mean":{"confidence_interval":{"confidence_level":0.95,"lower_bound":44984458.1875,"upper_bound":45315707.805},"point_estimate":45148745.64,"standard_error":84634.0355936316},"median":{"confidence_interval":{"confidence_level":0.95,"lower_bound":44862553.0,"upper_bound":45344612.25},"point_estimate":45099006.0,"standard_error":123846.77714484747},"median_abs_dev":{"confidence_interval":{"confidence_level":0.95,"lower_bound":799849.713049829,"upper_bound":1197839.5912840962},"point_estimate":1086409.601162374,"standard_error":103126.4938477633},"slope":null,"std_dev":{"confidence_interval":{"confidence_level":0.95,"lower_bound":753387.7687325997,"upper_bound":940010.2566155549},"point_estimate":852827.9714469168,"standard_error":47612.94444087438}}