{"mean":{"confidence_interval":{"confidence_level":0.95,"lower_bound":41473184.822,"upper_bound":41730925.535},"point_estimate":41598725.245,"standard_error":65759.95803233914},"median":{"confidence_interval":{"confidence_level":0.95,"lower_bound":41401460.75,"upper_bound":41558396.5},"point_estimate":41484212.5,"standard_error":48981.905771164675},"median_abs_dev":{"confidence_interval":{"confidence_level":0.95,"lower_bound":326296.53260707855,"upper_bound":563540.4198076574},"point_estimate":431854.6855330467,"standard_error":60152.7655783451},"slope":null,"std_dev":{"confidence_interval":{"confidence_level":0.95,"lower_bound":517149.96962344035,"upper_bound":793263.6759197593},"point_estimate":663061.2486061173,"standard_error":70369.96256873531}}