{"mean":{"confidence_interval":{"confidence_level":0.95,"lower_bound":8985.835462896344,"upper_bound":9145.101565202607},"point_estimate":9059.105820906512,"standard_error":40.548619457015505},"median":{"confidence_interval":{"confidence_level":0.95,"lower_bound":8888.74107142857,"upper_bound":9149.455858747993},"point_estimate":9012.481167247388,"standard_error":84.53893563449985},"median_abs_dev":{"confidence_interval":{"confidence_level":0.95,"lower_bound":229.08637660250295,"upper_bound":379.4044691795971},"point_estimate":268.72192789860077,"standard_error":39.6929264416971},"slope":{"confidence_interval":{"confidence_level":0.95,"lower_bound":8995.5796746294,"upper_bound":9165.33947964628},"point_estimate":9070.467164390213,"standard_error":43.59429812836653},"std_dev":{"confidence_interval":{"confidence_level":0.95,"lower_bound":243.29574052629772,"upper_bound":581.6047443828592},"point_estimate":408.0018719179505,"standard_error":92.17807857928078}}