{"mean":{"confidence_interval":{"confidence_level":0.95,"lower_bound":2365559.269806818,"upper_bound":2367188.739454545},"point_estimate":2366371.206818181,"standard_error":415.88238142644167},"median":{"confidence_interval":{"confidence_level":0.95,"lower_bound":2365244.409090909,"upper_bound":2367242.75},"point_estimate":2366217.7272727275,"standard_error":499.7888431071356},"median_abs_dev":{"confidence_interval":{"confidence_level":0.95,"lower_bound":2349.112267385892,"upper_bound":3651.7111260785414},"point_estimate":2901.2122803115876,"standard_error":317.04244573054217},"slope":null,"std_dev":{"confidence_interval":{"confidence_level":0.95,"lower_bound":3120.278396404858,"upper_bound":5114.658218502252},"point_estimate":4165.382296614593,"standard_error":508.70320512655775}}