{"mean":{"confidence_interval":{"confidence_level":0.95,"lower_bound":79597.88538731077,"upper_bound":80735.30815239104},"point_estimate":80014.33234325878,"standard_error":321.3997614283422},"median":{"confidence_interval":{"confidence_level":0.95,"lower_bound":79576.10476190476,"upper_bound":79737.56570048309},"point_estimate":79635.95491400492,"standard_error":40.11867832371441},"median_abs_dev":{"confidence_interval":{"confidence_level":0.95,"lower_bound":236.69299420695407,"upper_bound":471.7621683260423},"point_estimate":316.6313671059389,"standard_error":59.59488153619489},"slope":{"confidence_interval":{"confidence_level":0.95,"lower_bound":79766.2031337178,"upper_bound":80116.03112744846},"point_estimate":79921.06265110093,"standard_error":89.96248944917065},"std_dev":{"confidence_interval":{"confidence_level":0.95,"lower_bound":417.94957277884015,"upper_bound":5475.292679588669},"point_estimate":3235.7934440070485,"standard_error":1701.4209042732532}}