{"mean":{"confidence_interval":{"confidence_level":0.95,"lower_bound":6923.26210424324,"upper_bound":6942.472108465099},"point_estimate":6932.058986163571,"standard_error":4.926077247197266},"median":{"confidence_interval":{"confidence_level":0.95,"lower_bound":6917.292045454546,"upper_bound":6931.179121549489},"point_estimate":6923.822893939394,"standard_error":3.533060190225366},"median_abs_dev":{"confidence_interval":{"confidence_level":0.95,"lower_bound":22.811584740775924,"upper_bound":39.509848715564445},"point_estimate":31.580656122664916,"standard_error":4.352679254988512},"slope":{"confidence_interval":{"confidence_level":0.95,"lower_bound":6926.249606656041,"upper_bound":6943.1028694526},"point_estimate":6934.1206901137875,"standard_error":4.304520759652364},"std_dev":{"confidence_interval":{"confidence_level":0.95,"lower_bound":29.746293030609323,"upper_bound":69.24760988947612},"point_estimate":49.456252476925506,"standard_error":10.49921193728156}}