{"mean":{"confidence_interval":{"confidence_level":0.95,"lower_bound":6933.311045919992,"upper_bound":6948.084322840099},"point_estimate":6940.490286017255,"standard_error":3.7769329926492388},"median":{"confidence_interval":{"confidence_level":0.95,"lower_bound":6927.943157894737,"upper_bound":6939.485884218873},"point_estimate":6933.4306349206345,"standard_error":3.070361674349109},"median_abs_dev":{"confidence_interval":{"confidence_level":0.95,"lower_bound":26.55211645168256,"upper_bound":41.22857015284156},"point_estimate":35.159679623798,"standard_error":3.8671437942495364},"slope":{"confidence_interval":{"confidence_level":0.95,"lower_bound":6939.204418325957,"upper_bound":6957.368830486086},"point_estimate":6947.644641643269,"standard_error":4.660278858537084},"std_dev":{"confidence_interval":{"confidence_level":0.95,"lower_bound":30.684737056234706,"upper_bound":44.749612649089855},"point_estimate":38.08669323276193,"standard_error":3.5859218626282936}}