{"mean":{"confidence_interval":{"confidence_level":0.95,"lower_bound":10451.334211341307,"upper_bound":10460.300190175132},"point_estimate":10455.676945024135,"standard_error":2.279681388980022},"median":{"confidence_interval":{"confidence_level":0.95,"lower_bound":10450.0,"upper_bound":10459.299093397196},"point_estimate":10456.209530279502,"standard_error":2.7740134049801357},"median_abs_dev":{"confidence_interval":{"confidence_level":0.95,"lower_bound":18.476172075945765,"upper_bound":28.982728635250233},"point_estimate":25.87117026650101,"standard_error":2.8086208487604414},"slope":{"confidence_interval":{"confidence_level":0.95,"lower_bound":10455.210280532852,"upper_bound":10462.087287441034},"point_estimate":10458.652020097532,"standard_error":1.745232935123162},"std_dev":{"confidence_interval":{"confidence_level":0.95,"lower_bound":18.06727663926792,"upper_bound":28.459887794308568},"point_estimate":23.00764474100709,"standard_error":2.7271778390119366}}