{"mean":{"confidence_interval":{"confidence_level":0.95,"lower_bound":311545.4612782109,"upper_bound":314667.0394821118},"point_estimate":312947.0896065463,"standard_error":801.487206742879},"median":{"confidence_interval":{"confidence_level":0.95,"lower_bound":310692.92264647793,"upper_bound":310781.27243589744},"point_estimate":310723.82109375,"standard_error":25.38227594892334},"median_abs_dev":{"confidence_interval":{"confidence_level":0.95,"lower_bound":138.32931355709084,"upper_bound":259.4694231073339},"point_estimate":194.3925854909741,"standard_error":32.384737867811204},"slope":{"confidence_interval":{"confidence_level":0.95,"lower_bound":311403.1472531358,"upper_bound":315389.595251732},"point_estimate":313168.1470732969,"standard_error":1024.9435029318627},"std_dev":{"confidence_interval":{"confidence_level":0.95,"lower_bound":3914.474735074507,"upper_bound":11435.60040556222},"point_estimate":8013.28661960642,"standard_error":1935.1601337470659}}