{"mean":{"confidence_interval":{"confidence_level":0.95,"lower_bound":21321065.021583326,"upper_bound":21697884.01799999},"point_estimate":21503283.40333333,"standard_error":95497.38316394566},"median":{"confidence_interval":{"confidence_level":0.95,"lower_bound":21024354.333333332,"upper_bound":21628724.333333332},"point_estimate":21330156.0,"standard_error":131594.99502666437},"median_abs_dev":{"confidence_interval":{"confidence_level":0.95,"lower_bound":663739.4989162702,"upper_bound":1080011.0703259706},"point_estimate":944124.8523384333,"standard_error":105021.59643031358},"slope":null,"std_dev":{"confidence_interval":{"confidence_level":0.95,"lower_bound":763727.8877325687,"upper_bound":1153200.512392205},"point_estimate":958492.9408722026,"standard_error":100686.74944034546}}