{"mean":{"confidence_interval":{"confidence_level":0.95,"lower_bound":20162690.15850001,"upper_bound":20330825.818416674},"point_estimate":20246486.72,"standard_error":42833.88325919012},"median":{"confidence_interval":{"confidence_level":0.95,"lower_bound":20155195.0,"upper_bound":20337945.166666668},"point_estimate":20272145.0,"standard_error":41804.99748613905},"median_abs_dev":{"confidence_interval":{"confidence_level":0.95,"lower_bound":382214.5141368349,"upper_bound":595610.3236258049},"point_estimate":494224.9483257523,"standard_error":54063.28953068378},"slope":null,"std_dev":{"confidence_interval":{"confidence_level":0.95,"lower_bound":375912.4196472403,"upper_bound":480017.3715479422},"point_estimate":430224.0869655689,"standard_error":26562.406682051576}}