{"mean":{"confidence_interval":{"confidence_level":0.95,"lower_bound":30203052.365,"upper_bound":30549651.021875},"point_estimate":30386485.695,"standard_error":88619.88790820826},"median":{"confidence_interval":{"confidence_level":0.95,"lower_bound":30472864.5,"upper_bound":30593901.75},"point_estimate":30515715.25,"standard_error":48930.33006037167},"median_abs_dev":{"confidence_interval":{"confidence_level":0.95,"lower_bound":623680.883127451,"upper_bound":796399.2488648369},"point_estimate":731789.1080081463,"standard_error":57161.61716656937},"slope":null,"std_dev":{"confidence_interval":{"confidence_level":0.95,"lower_bound":601543.9689871843,"upper_bound":1165820.1355523118},"point_estimate":894445.9714945776,"standard_error":145101.09526313274}}