{"mean":{"confidence_interval":{"confidence_level":0.95,"lower_bound":35614.97195557535,"upper_bound":35699.6318058105},"point_estimate":35651.29079649236,"standard_error":21.89423238315347},"median":{"confidence_interval":{"confidence_level":0.95,"lower_bound":35605.03367003367,"upper_bound":35626.56314935065},"point_estimate":35617.81772941971,"standard_error":6.704960673113042},"median_abs_dev":{"confidence_interval":{"confidence_level":0.95,"lower_bound":31.730572377428366,"upper_bound":55.356520864072955},"point_estimate":43.33581891148905,"standard_error":5.990636798180353},"slope":{"confidence_interval":{"confidence_level":0.95,"lower_bound":35612.44091585133,"upper_bound":35665.35851933055},"point_estimate":35633.80193438747,"standard_error":13.757626924446708},"std_dev":{"confidence_interval":{"confidence_level":0.95,"lower_bound":59.571796511428836,"upper_bound":339.12260712852805},"point_estimate":219.95333055600665,"standard_error":72.50289652178408}}