{"mean":{"confidence_interval":{"confidence_level":0.95,"lower_bound":31522780.66075,"upper_bound":32358397.97},"point_estimate":31948262.28,"standard_error":213160.4698209873},"median":{"confidence_interval":{"confidence_level":0.95,"lower_bound":32036855.0,"upper_bound":32804977.75},"point_estimate":32346873.75,"standard_error":207172.38694940158},"median_abs_dev":{"confidence_interval":{"confidence_level":0.95,"lower_bound":1413071.9653129578,"upper_bound":2500433.02500844},"point_estimate":1917924.6844500303,"standard_error":290305.58402024134},"slope":null,"std_dev":{"confidence_interval":{"confidence_level":0.95,"lower_bound":1766501.2982480952,"upper_bound":2470602.9042835683},"point_estimate":2137239.7383487406,"standard_error":179881.97753442565}}