{"mean":{"confidence_interval":{"confidence_level":0.95,"lower_bound":50329.55782024571,"upper_bound":50802.148863602335},"point_estimate":50593.8934206393,"standard_error":120.8373431592787},"median":{"confidence_interval":{"confidence_level":0.95,"lower_bound":50580.80630980861,"upper_bound":50891.240277777775},"point_estimate":50699.478676470586,"standard_error":76.35679619140522},"median_abs_dev":{"confidence_interval":{"confidence_level":0.95,"lower_bound":335.19976260539863,"upper_bound":515.58021891361},"point_estimate":443.3582405038187,"standard_error":46.60130772255419},"slope":{"confidence_interval":{"confidence_level":0.95,"lower_bound":50778.93025515792,"upper_bound":51069.08567349453},"point_estimate":50911.24384335747,"standard_error":74.35885255999311},"std_dev":{"confidence_interval":{"confidence_level":0.95,"lower_bound":570.4005637329789,"upper_bound":1830.476492225851},"point_estimate":1215.7136783031044,"standard_error":346.0460152646494}}