{"mean":{"confidence_interval":{"confidence_level":0.95,"lower_bound":85571.58854031806,"upper_bound":86983.02924743897},"point_estimate":86386.19375773892,"standard_error":364.62217845888995},"median":{"confidence_interval":{"confidence_level":0.95,"lower_bound":86934.4675925926,"upper_bound":87079.98148148147},"point_estimate":87009.30558631722,"standard_error":35.99395996887637},"median_abs_dev":{"confidence_interval":{"confidence_level":0.95,"lower_bound":285.1917454263502,"upper_bound":755.8218256849426},"point_estimate":404.1006430638059,"standard_error":128.4830580665959},"slope":{"confidence_interval":{"confidence_level":0.95,"lower_bound":87229.60153921401,"upper_bound":87690.84287677363},"point_estimate":87443.71159819713,"standard_error":118.39758925313845},"std_dev":{"confidence_interval":{"confidence_level":0.95,"lower_bound":1407.0352172686305,"upper_bound":5717.980680646667},"point_estimate":3660.250562502209,"standard_error":1225.4611192087311}}