{"mean":{"confidence_interval":{"confidence_level":0.95,"lower_bound":72718.09935736569,"upper_bound":74249.31899655891},"point_estimate":73569.68673267947,"standard_error":392.56005502032525},"median":{"confidence_interval":{"confidence_level":0.95,"lower_bound":73668.41836734694,"upper_bound":73846.76267281106},"point_estimate":73765.80639924592,"standard_error":48.331625970324275},"median_abs_dev":{"confidence_interval":{"confidence_level":0.95,"lower_bound":364.40896085425425,"upper_bound":950.2455718410064},"point_estimate":558.8951766525183,"standard_error":143.27366590644954},"slope":{"confidence_interval":{"confidence_level":0.95,"lower_bound":74143.58387597879,"upper_bound":74923.39918481336},"point_estimate":74500.68171399017,"standard_error":199.81249585188573},"std_dev":{"confidence_interval":{"confidence_level":0.95,"lower_bound":1942.564378469458,"upper_bound":5889.575087248792},"point_estimate":3941.8269722389855,"standard_error":1090.4195465725734}}