{"mean":{"confidence_interval":{"confidence_level":0.95,"lower_bound":69675.98914871854,"upper_bound":70993.43504311937},"point_estimate":70368.51174981125,"standard_error":335.64462787463196},"median":{"confidence_interval":{"confidence_level":0.95,"lower_bound":69644.67105263157,"upper_bound":70209.74609788359},"point_estimate":69863.5113997114,"standard_error":155.2912298841288},"median_abs_dev":{"confidence_interval":{"confidence_level":0.95,"lower_bound":788.1376248901194,"upper_bound":2576.178929112831},"point_estimate":1567.1872385468737,"standard_error":538.7696281343364},"slope":{"confidence_interval":{"confidence_level":0.95,"lower_bound":70400.41685604306,"upper_bound":71435.06802602913},"point_estimate":70891.32516230727,"standard_error":263.7444152449146},"std_dev":{"confidence_interval":{"confidence_level":0.95,"lower_bound":2179.165150077421,"upper_bound":4627.293452666331},"point_estimate":3382.006153553074,"standard_error":649.7441192756714}}