{"mean":{"confidence_interval":{"confidence_level":0.95,"lower_bound":70135.60580429039,"upper_bound":71670.32241189777},"point_estimate":70923.65375628721,"standard_error":390.82765944580416},"median":{"confidence_interval":{"confidence_level":0.95,"lower_bound":70548.50661375662,"upper_bound":70889.51319875776},"point_estimate":70652.34229262674,"standard_error":88.50833208752388},"median_abs_dev":{"confidence_interval":{"confidence_level":0.95,"lower_bound":585.2474195713207,"upper_bound":1482.7226608463163},"point_estimate":1032.632352500443,"standard_error":242.38775094146848},"slope":{"confidence_interval":{"confidence_level":0.95,"lower_bound":71217.83252107231,"upper_bound":72831.71370632853},"point_estimate":71888.14427748106,"standard_error":419.35457161297296},"std_dev":{"confidence_interval":{"confidence_level":0.95,"lower_bound":2460.100639114153,"upper_bound":5325.269156633598},"point_estimate":3924.4991580804913,"standard_error":744.150108091119}}