{"mean":{"confidence_interval":{"confidence_level":0.95,"lower_bound":74767.0206317286,"upper_bound":76371.49469518532},"point_estimate":75511.4366244608,"standard_error":409.5009617099282},"median":{"confidence_interval":{"confidence_level":0.95,"lower_bound":74351.94101223978,"upper_bound":75038.84415584416},"point_estimate":74681.34863368099,"standard_error":188.061729857911},"median_abs_dev":{"confidence_interval":{"confidence_level":0.95,"lower_bound":902.3074913452311,"upper_bound":1993.5242988470013},"point_estimate":1407.8994496906048,"standard_error":289.8476836869728},"slope":{"confidence_interval":{"confidence_level":0.95,"lower_bound":75248.50227255673,"upper_bound":76186.32111183775},"point_estimate":75700.42835229791,"standard_error":239.67665458171098},"std_dev":{"confidence_interval":{"confidence_level":0.95,"lower_bound":2302.957104058888,"upper_bound":5651.566602943337},"point_estimate":4091.502740352814,"standard_error":853.9877939661193}}