{"mean":{"confidence_interval":{"confidence_level":0.95,"lower_bound":69021.76772366899,"upper_bound":70583.99862240642},"point_estimate":69860.19203288462,"standard_error":399.290620815574},"median":{"confidence_interval":{"confidence_level":0.95,"lower_bound":69066.06953405018,"upper_bound":69677.8947368421},"point_estimate":69279.6003927004,"standard_error":132.82754986924596},"median_abs_dev":{"confidence_interval":{"confidence_level":0.95,"lower_bound":727.2189893843824,"upper_bound":1853.8237154529863},"point_estimate":1042.4231036033232,"standard_error":322.0511197500465},"slope":{"confidence_interval":{"confidence_level":0.95,"lower_bound":70350.89796494017,"upper_bound":71651.63148161449},"point_estimate":70984.38487759224,"standard_error":332.08107252685215},"std_dev":{"confidence_interval":{"confidence_level":0.95,"lower_bound":2498.4416875083202,"upper_bound":5649.939441361014},"point_estimate":4002.8592352907804,"standard_error":869.827720176626}}