{"mean":{"confidence_interval":{"confidence_level":0.95,"lower_bound":100687611.61575,"upper_bound":101114108.83125},"point_estimate":100899201.64,"standard_error":108922.62001065002},"median":{"confidence_interval":{"confidence_level":0.95,"lower_bound":100484090.0,"upper_bound":101136604.0},"point_estimate":100888717.0,"standard_error":168057.9040969928},"median_abs_dev":{"confidence_interval":{"confidence_level":0.95,"lower_bound":897668.3234632015,"upper_bound":1428284.182342887},"point_estimate":1131024.3702203035,"standard_error":139052.23628834475},"slope":null,"std_dev":{"confidence_interval":{"confidence_level":0.95,"lower_bound":963163.9144367517,"upper_bound":1214872.9757400246},"point_estimate":1097273.7932952812,"standard_error":64588.569410717035}}