{"mean":{"confidence_interval":{"confidence_level":0.95,"lower_bound":68235.47998390372,"upper_bound":68953.7102883752},"point_estimate":68566.85181387927,"standard_error":183.82142598412236},"median":{"confidence_interval":{"confidence_level":0.95,"lower_bound":67685.29444928377,"upper_bound":67918.82492492493},"point_estimate":67792.83457991804,"standard_error":66.54333240828626},"median_abs_dev":{"confidence_interval":{"confidence_level":0.95,"lower_bound":382.93383519469523,"upper_bound":884.7398768375224},"point_estimate":561.5931222892671,"standard_error":131.14553181846975},"slope":{"confidence_interval":{"confidence_level":0.95,"lower_bound":67684.26983580299,"upper_bound":68190.34767284116},"point_estimate":67902.30565834195,"standard_error":129.9956227097113},"std_dev":{"confidence_interval":{"confidence_level":0.95,"lower_bound":1190.9652707655666,"upper_bound":2540.990706348894},"point_estimate":1848.9694183079466,"standard_error":364.2340143082877}}