{"mean":{"confidence_interval":{"confidence_level":0.95,"lower_bound":9878179.01279167,"upper_bound":10090529.844541667},"point_estimate":9955609.833333332,"standard_error":59656.59533111147},"median":{"confidence_interval":{"confidence_level":0.95,"lower_bound":9871981.0,"upper_bound":9894464.0},"point_estimate":9885030.583333332,"standard_error":5985.692856308056},"median_abs_dev":{"confidence_interval":{"confidence_level":0.95,"lower_bound":30282.329941130232,"upper_bound":61761.96746725764},"point_estimate":43636.994375287104,"standard_error":8091.182618963754},"slope":null,"std_dev":{"confidence_interval":{"confidence_level":0.95,"lower_bound":62043.73953318151,"upper_bound":1011697.8383778492},"point_estimate":598474.9302591756,"standard_error":312292.56297349924}}