{"mean":{"confidence_interval":{"confidence_level":0.95,"lower_bound":55958057.716,"upper_bound":58202372.7455},"point_estimate":57004846.24,"standard_error":574678.3763705775},"median":{"confidence_interval":{"confidence_level":0.95,"lower_bound":54305682.0,"upper_bound":55889990.0},"point_estimate":54782200.0,"standard_error":373295.0702158088},"median_abs_dev":{"confidence_interval":{"confidence_level":0.95,"lower_bound":1829067.6495775592,"upper_bound":3661123.4794020653},"point_estimate":2396344.869956374,"standard_error":441536.98440191447},"slope":null,"std_dev":{"confidence_interval":{"confidence_level":0.95,"lower_bound":3879447.8346401104,"upper_bound":7799343.162526107},"point_estimate":5768228.370299381,"standard_error":1077940.5215224177}}