{"mean":{"confidence_interval":{"confidence_level":0.95,"lower_bound":8975555.988624997,"upper_bound":9002558.826750001},"point_estimate":8988483.336666666,"standard_error":6859.6524857519225},"median":{"confidence_interval":{"confidence_level":0.95,"lower_bound":8971845.583333332,"upper_bound":8990895.583333332},"point_estimate":8980720.0,"standard_error":4875.913484110333},"median_abs_dev":{"confidence_interval":{"confidence_level":0.95,"lower_bound":37015.08514285042,"upper_bound":67186.36525720311},"point_estimate":50507.23910331772,"standard_error":7501.304952392341},"slope":null,"std_dev":{"confidence_interval":{"confidence_level":0.95,"lower_bound":50810.353521489145,"upper_bound":88837.62824774976},"point_estimate":68867.23825073006,"standard_error":10063.610476442402}}