{"mean":{"confidence_interval":{"confidence_level":0.95,"lower_bound":374830.81343811954,"upper_bound":376650.70960833674},"point_estimate":375699.7783616614,"standard_error":434.2056588643055},"median":{"confidence_interval":{"confidence_level":0.95,"lower_bound":375603.1415190834,"upper_bound":375626.537630994},"point_estimate":375612.484006734,"standard_error":6.9626240398426225},"median_abs_dev":{"confidence_interval":{"confidence_level":0.95,"lower_bound":36.23108005607572,"upper_bound":66.39557220854974},"point_estimate":49.323574387478224,"standard_error":7.826567678620142},"slope":{"confidence_interval":{"confidence_level":0.95,"lower_bound":375629.9289355059,"upper_bound":376818.9825026956},"point_estimate":375999.5129303975,"standard_error":353.42074108087127},"std_dev":{"confidence_interval":{"confidence_level":0.95,"lower_bound":111.41577005084088,"upper_bound":7039.91067656051},"point_estimate":4363.598149684448,"standard_error":1887.8350538765246}}