{"mean":{"confidence_interval":{"confidence_level":0.95,"lower_bound":55758706.98,"upper_bound":56000349.64},"point_estimate":55872778.83,"standard_error":61210.33091728162},"median":{"confidence_interval":{"confidence_level":0.95,"lower_bound":55714202.0,"upper_bound":55903707.0},"point_estimate":55812842.0,"standard_error":42093.05060665619},"median_abs_dev":{"confidence_interval":{"confidence_level":0.95,"lower_bound":293943.9772814512,"upper_bound":491245.4165786505},"point_estimate":379649.37525987625,"standard_error":50561.754649245595},"slope":null,"std_dev":{"confidence_interval":{"confidence_level":0.95,"lower_bound":408521.1339498659,"upper_bound":846945.7655903416},"point_estimate":615738.8326146218,"standard_error":119492.11542205811}}