{"mean":{"confidence_interval":{"confidence_level":0.95,"lower_bound":198758529.344,"upper_bound":200870918.121},"point_estimate":199770133.47,"standard_error":540970.2770900626},"median":{"confidence_interval":{"confidence_level":0.95,"lower_bound":197407565.0,"upper_bound":199240221.5},"point_estimate":198368067.5,"standard_error":419565.77392752026},"median_abs_dev":{"confidence_interval":{"confidence_level":0.95,"lower_bound":3024621.071702242,"upper_bound":4972788.571715355},"point_estimate":3933729.8778623343,"standard_error":488694.1458505776},"slope":null,"std_dev":{"confidence_interval":{"confidence_level":0.95,"lower_bound":4258531.1002049465,"upper_bound":6590711.549201245},"point_estimate":5440439.724547682,"standard_error":599764.8932685283}}