{"mean":{"confidence_interval":{"confidence_level":0.95,"lower_bound":65441.050537633106,"upper_bound":66379.12004000782},"point_estimate":65848.15067228726,"standard_error":241.76534320836043},"median":{"confidence_interval":{"confidence_level":0.95,"lower_bound":64938.57028003613,"upper_bound":65385.4406277245},"point_estimate":65067.96589115081,"standard_error":100.80636784812299},"median_abs_dev":{"confidence_interval":{"confidence_level":0.95,"lower_bound":363.26059389524823,"upper_bound":984.8485476613743},"point_estimate":580.6973446905603,"standard_error":147.69098385256882},"slope":{"confidence_interval":{"confidence_level":0.95,"lower_bound":64951.71719376721,"upper_bound":66294.60309138564},"point_estimate":65499.37004581055,"standard_error":350.48867832557886},"std_dev":{"confidence_interval":{"confidence_level":0.95,"lower_bound":1022.6246182915283,"upper_bound":3688.969740391455},"point_estimate":2423.519583576605,"standard_error":730.5084568808958}}