{"mean":{"confidence_interval":{"confidence_level":0.95,"lower_bound":6631084.1483125,"upper_bound":6713849.75609375},"point_estimate":6669742.0725,"standard_error":21131.853632274237},"median":{"confidence_interval":{"confidence_level":0.95,"lower_bound":6558833.0,"upper_bound":6593546.875},"point_estimate":6562248.0625,"standard_error":8721.798570230276},"median_abs_dev":{"confidence_interval":{"confidence_level":0.95,"lower_bound":8414.496150612831,"upper_bound":59493.49375627935},"point_estimate":15041.254720464349,"standard_error":12922.03063777484},"slope":null,"std_dev":{"confidence_interval":{"confidence_level":0.95,"lower_bound":144648.26545923908,"upper_bound":270201.01154407754},"point_estimate":212879.79499075958,"standard_error":32039.5692141838}}