{"mean":{"confidence_interval":{"confidence_level":0.95,"lower_bound":6565245.341843749,"upper_bound":6576037.19375},"point_estimate":6569550.38,"standard_error":2830.3818238888794},"median":{"confidence_interval":{"confidence_level":0.95,"lower_bound":6561893.875,"upper_bound":6565055.875},"point_estimate":6563534.25,"standard_error":823.1006781622012},"median_abs_dev":{"confidence_interval":{"confidence_level":0.95,"lower_bound":5425.389278680086,"upper_bound":9790.812238678336},"point_estimate":7680.516501143575,"standard_error":1080.55416166005},"slope":null,"std_dev":{"confidence_interval":{"confidence_level":0.95,"lower_bound":9743.242007930601,"upper_bound":45655.47753625097},"point_estimate":28201.047932057405,"standard_error":11698.11540802608}}