{"mean":{"confidence_interval":{"confidence_level":0.95,"lower_bound":155757132.246,"upper_bound":156374508.27975002},"point_estimate":156052382.41,"standard_error":156569.94320138794},"median":{"confidence_interval":{"confidence_level":0.95,"lower_bound":155551919.0,"upper_bound":156351717.0},"point_estimate":155863516.0,"standard_error":235762.29574313198},"median_abs_dev":{"confidence_interval":{"confidence_level":0.95,"lower_bound":1058994.5114640896,"upper_bound":1573819.1609591246},"point_estimate":1330145.7009851933,"standard_error":132888.85279222875},"slope":null,"std_dev":{"confidence_interval":{"confidence_level":0.95,"lower_bound":1133950.3775332735,"upper_bound":2076570.8474664127},"point_estimate":1577450.50003918,"standard_error":253589.9959699092}}