{"mean":{"confidence_interval":{"confidence_level":0.95,"lower_bound":77471868.98675,"upper_bound":78104918.6825},"point_estimate":77787470.85,"standard_error":162454.53056960108},"median":{"confidence_interval":{"confidence_level":0.95,"lower_bound":77307065.0,"upper_bound":78217294.0},"point_estimate":77734557.5,"standard_error":215793.7474373241},"median_abs_dev":{"confidence_interval":{"confidence_level":0.95,"lower_bound":1239615.1813924313,"upper_bound":2114485.565060377},"point_estimate":1526132.0741057396,"standard_error":229471.9070736089},"slope":null,"std_dev":{"confidence_interval":{"confidence_level":0.95,"lower_bound":1409775.575041561,"upper_bound":1836970.9231511853},"point_estimate":1635876.452520544,"standard_error":109005.94780461503}}