{"mean":{"confidence_interval":{"confidence_level":0.95,"lower_bound":6447360.341375,"upper_bound":6465946.31040625},"point_estimate":6456228.38625,"standard_error":4720.377219398136},"median":{"confidence_interval":{"confidence_level":0.95,"lower_bound":6442578.5625,"upper_bound":6463631.625},"point_estimate":6455633.6875,"standard_error":5363.500301718231},"median_abs_dev":{"confidence_interval":{"confidence_level":0.95,"lower_bound":27461.735999956727,"upper_bound":42204.98812571168},"point_estimate":33602.01645344496,"standard_error":3611.254399727726},"slope":null,"std_dev":{"confidence_interval":{"confidence_level":0.95,"lower_bound":33742.204850785805,"upper_bound":60825.03878596704},"point_estimate":47292.59103225935,"standard_error":6995.619665504208}}