{"mean":{"confidence_interval":{"confidence_level":0.95,"lower_bound":79535.18281041105,"upper_bound":79729.66672258204},"point_estimate":79629.17200105985,"standard_error":49.54528468654354},"median":{"confidence_interval":{"confidence_level":0.95,"lower_bound":79529.74375,"upper_bound":79714.39288194444},"point_estimate":79613.22688524591,"standard_error":48.93634425267008},"median_abs_dev":{"confidence_interval":{"confidence_level":0.95,"lower_bound":268.08347895827717,"upper_bound":450.39010565800316},"point_estimate":350.9881552501874,"standard_error":45.70626715660874},"slope":{"confidence_interval":{"confidence_level":0.95,"lower_bound":79685.9522430854,"upper_bound":79797.27822346381},"point_estimate":79739.89690793557,"standard_error":28.492031750601587},"std_dev":{"confidence_interval":{"confidence_level":0.95,"lower_bound":367.1502169445849,"upper_bound":630.969019428113},"point_estimate":497.00507624091273,"standard_error":68.6272559194525}}