{"mean":{"confidence_interval":{"confidence_level":0.95,"lower_bound":47368419.75975,"upper_bound":47578000.187375},"point_estimate":47472090.29,"standard_error":53439.07026897973},"median":{"confidence_interval":{"confidence_level":0.95,"lower_bound":47290616.75,"upper_bound":47464244.0},"point_estimate":47347617.5,"standard_error":44051.1950180357},"median_abs_dev":{"confidence_interval":{"confidence_level":0.95,"lower_bound":336183.99183154106,"upper_bound":647718.6471506953},"point_estimate":488485.9273776412,"standard_error":83225.88732988207},"slope":null,"std_dev":{"confidence_interval":{"confidence_level":0.95,"lower_bound":458706.38876952487,"upper_bound":607008.6452200658},"point_estimate":537838.0342637295,"standard_error":37995.574351166935}}