{"mean":{"confidence_interval":{"confidence_level":0.95,"lower_bound":6510854.88053125,"upper_bound":6514984.852093751},"point_estimate":6512771.6525,"standard_error":1053.9879415188916},"median":{"confidence_interval":{"confidence_level":0.95,"lower_bound":6509613.625,"upper_bound":6513344.9375},"point_estimate":6510837.6875,"standard_error":885.2832371241029},"median_abs_dev":{"confidence_interval":{"confidence_level":0.95,"lower_bound":5588.753263279796,"upper_bound":9314.295340888191},"point_estimate":7338.77720721066,"standard_error":914.372100843056},"slope":null,"std_dev":{"confidence_interval":{"confidence_level":0.95,"lower_bound":7050.875675874027,"upper_bound":14581.21745500664},"point_estimate":10589.251457899658,"standard_error":2117.4201689757074}}