{"mean":{"confidence_interval":{"confidence_level":0.95,"lower_bound":6582.00845460156,"upper_bound":6617.988098953792},"point_estimate":6597.864362440064,"standard_error":9.256986958742313},"median":{"confidence_interval":{"confidence_level":0.95,"lower_bound":6572.6179104477615,"upper_bound":6590.257692307692},"point_estimate":6580.627660818713,"standard_error":3.9773618091967977},"median_abs_dev":{"confidence_interval":{"confidence_level":0.95,"lower_bound":29.075989059555848,"upper_bound":52.05964874870086},"point_estimate":40.09581270935993,"standard_error":5.79302094023218},"slope":{"confidence_interval":{"confidence_level":0.95,"lower_bound":6605.732442402538,"upper_bound":6670.968850472399},"point_estimate":6633.390225309098,"standard_error":16.882407514255945},"std_dev":{"confidence_interval":{"confidence_level":0.95,"lower_bound":43.164944935498006,"upper_bound":141.76014736871562},"point_estimate":93.12107044404158,"standard_error":27.767169186958636}}