{"mean":{"confidence_interval":{"confidence_level":0.95,"lower_bound":7484.008284732689,"upper_bound":7495.041952310088},"point_estimate":7489.266911298912,"standard_error":2.8142554408414755},"median":{"confidence_interval":{"confidence_level":0.95,"lower_bound":7486.027272727273,"upper_bound":7493.6578947368425},"point_estimate":7490.425156641604,"standard_error":1.7294315920504477},"median_abs_dev":{"confidence_interval":{"confidence_level":0.95,"lower_bound":11.333036597193265,"upper_bound":20.291616306418486},"point_estimate":15.636966998811243,"standard_error":2.349290152462539},"slope":{"confidence_interval":{"confidence_level":0.95,"lower_bound":7471.421195691273,"upper_bound":7493.731503406244},"point_estimate":7481.116371114724,"standard_error":5.72596917721587},"std_dev":{"confidence_interval":{"confidence_level":0.95,"lower_bound":19.096968690648307,"upper_bound":38.73000382462584},"point_estimate":28.168396577788254,"standard_error":5.531220360176225}}