{"mean":{"confidence_interval":{"confidence_level":0.95,"lower_bound":85210099.82375,"upper_bound":85512557.8325},"point_estimate":85359612.37,"standard_error":77235.14458040627},"median":{"confidence_interval":{"confidence_level":0.95,"lower_bound":85171063.5,"upper_bound":85452180.5},"point_estimate":85312815.0,"standard_error":77061.52269250488},"median_abs_dev":{"confidence_interval":{"confidence_level":0.95,"lower_bound":518228.7360996008,"upper_bound":929567.94449687},"point_estimate":758836.1793279648,"standard_error":107488.23596995398},"slope":null,"std_dev":{"confidence_interval":{"confidence_level":0.95,"lower_bound":629367.0070740872,"upper_bound":925032.6990512292},"point_estimate":774654.2214872995,"standard_error":76411.0311761716}}