{"mean":{"confidence_interval":{"confidence_level":0.95,"lower_bound":88405949.3895,"upper_bound":89022481.239},"point_estimate":88693245.25,"standard_error":157748.28831087062},"median":{"confidence_interval":{"confidence_level":0.95,"lower_bound":88124630.0,"upper_bound":88506235.925},"point_estimate":88324182.5,"standard_error":101830.5940510615},"median_abs_dev":{"confidence_interval":{"confidence_level":0.95,"lower_bound":680903.3117115498,"upper_bound":1223211.6952836514},"point_estimate":905717.3587203026,"standard_error":145053.4252368166},"slope":null,"std_dev":{"confidence_interval":{"confidence_level":0.95,"lower_bound":978016.8348165898,"upper_bound":2095561.4084784086},"point_estimate":1591376.4896269713,"standard_error":282330.23649600626}}