{"mean":{"confidence_interval":{"confidence_level":0.95,"lower_bound":16954900.89608332,"upper_bound":17139253.66125},"point_estimate":17048436.203333333,"standard_error":47032.6590287617},"median":{"confidence_interval":{"confidence_level":0.95,"lower_bound":16928427.833333332,"upper_bound":17220887.333333332},"point_estimate":17082578.666666668,"standard_error":79260.95895619584},"median_abs_dev":{"confidence_interval":{"confidence_level":0.95,"lower_bound":452256.7437708364,"upper_bound":705326.6752779479},"point_estimate":589495.3400343619,"standard_error":65023.928330840274},"slope":null,"std_dev":{"confidence_interval":{"confidence_level":0.95,"lower_bound":416919.083196846,"upper_bound":521657.9153305922},"point_estimate":472494.8947509608,"standard_error":26786.90179000605}}