{"mean":{"confidence_interval":{"confidence_level":0.95,"lower_bound":18840382.762499996,"upper_bound":18891848.838750016},"point_estimate":18866908.983333338,"standard_error":13107.497254955562},"median":{"confidence_interval":{"confidence_level":0.95,"lower_bound":18862289.666666668,"upper_bound":18928390.166666664},"point_estimate":18896289.833333336,"standard_error":15947.870756714918},"median_abs_dev":{"confidence_interval":{"confidence_level":0.95,"lower_bound":83619.37981546478,"upper_bound":139563.0720997601},"point_estimate":121277.6662468901,"standard_error":14003.478887991725},"slope":null,"std_dev":{"confidence_interval":{"confidence_level":0.95,"lower_bound":105640.69148069473,"upper_bound":155888.85632357906},"point_estimate":132030.26181719103,"standard_error":12849.8884484191}}