{"mean":{"confidence_interval":{"confidence_level":0.95,"lower_bound":52717.11297087128,"upper_bound":52782.92950230342},"point_estimate":52749.53052102755,"standard_error":16.809093138482382},"median":{"confidence_interval":{"confidence_level":0.95,"lower_bound":52709.9453125,"upper_bound":52784.27475543479},"point_estimate":52754.67556818182,"standard_error":20.21047480472227},"median_abs_dev":{"confidence_interval":{"confidence_level":0.95,"lower_bound":120.39661170464285,"upper_bound":204.57248893651524},"point_estimate":171.94072115198884,"standard_error":21.45707566602604},"slope":{"confidence_interval":{"confidence_level":0.95,"lower_bound":52788.208199063236,"upper_bound":52863.38276052042},"point_estimate":52825.266163735774,"standard_error":19.2196441449123},"std_dev":{"confidence_interval":{"confidence_level":0.95,"lower_bound":142.44403350197058,"upper_bound":192.87320598523638},"point_estimate":168.73316987348926,"standard_error":12.918225393019663}}