{"mean":{"confidence_interval":{"confidence_level":0.95,"lower_bound":56913488.522999994,"upper_bound":57484513.99},"point_estimate":57183384.29,"standard_error":144993.7821915171},"median":{"confidence_interval":{"confidence_level":0.95,"lower_bound":57249239.0,"upper_bound":57700244.0},"point_estimate":57629216.0,"standard_error":128632.18810417248},"median_abs_dev":{"confidence_interval":{"confidence_level":0.95,"lower_bound":458004.7838687897,"upper_bound":1184965.0637626648},"point_estimate":738657.9936861992,"standard_error":192264.21690332095},"slope":null,"std_dev":{"confidence_interval":{"confidence_level":0.95,"lower_bound":922492.8127909868,"upper_bound":2053488.491038816},"point_estimate":1449044.1432437787,"standard_error":313497.4888984829}}