{"mean":{"confidence_interval":{"confidence_level":0.95,"lower_bound":4871224.121568181,"upper_bound":4878756.004386363},"point_estimate":4874668.1018181825,"standard_error":1926.6920145495574},"median":{"confidence_interval":{"confidence_level":0.95,"lower_bound":4866032.818181818,"upper_bound":4871708.727272727},"point_estimate":4868495.045454545,"standard_error":1459.2363128829265},"median_abs_dev":{"confidence_interval":{"confidence_level":0.95,"lower_bound":7273.702861774298,"upper_bound":13457.964306527541},"point_estimate":10465.807996012822,"standard_error":1554.2843475529983},"slope":null,"std_dev":{"confidence_interval":{"confidence_level":0.95,"lower_bound":12346.678438190065,"upper_bound":26976.084387829305},"point_estimate":19373.82030393313,"standard_error":4169.815234728537}}