{"mean":{"confidence_interval":{"confidence_level":0.95,"lower_bound":8460290.89166667,"upper_bound":8478760.526666665},"point_estimate":8469380.631666671,"standard_error":4717.95809330754},"median":{"confidence_interval":{"confidence_level":0.95,"lower_bound":8455512.0,"upper_bound":8473059.5},"point_estimate":8461758.583333332,"standard_error":5271.1879542806355},"median_abs_dev":{"confidence_interval":{"confidence_level":0.95,"lower_bound":30112.346765396218,"upper_bound":53832.13633678764},"point_estimate":43319.71798092403,"standard_error":6060.746622580887},"slope":null,"std_dev":{"confidence_interval":{"confidence_level":0.95,"lower_bound":39302.497092378995,"upper_bound":54999.13829402459},"point_estimate":47489.49029600972,"standard_error":4017.813463901782}}