{"mean":{"confidence_interval":{"confidence_level":0.95,"lower_bound":2655598.891171053,"upper_bound":2656878.0119078932},"point_estimate":2656174.4284210526,"standard_error":327.8166796096965},"median":{"confidence_interval":{"confidence_level":0.95,"lower_bound":2655219.8421052634,"upper_bound":2655914.5789473685},"point_estimate":2655669.842105263,"standard_error":176.0985591461427},"median_abs_dev":{"confidence_interval":{"confidence_level":0.95,"lower_bound":1092.3640542906176,"upper_bound":1845.4468093422329},"point_estimate":1408.4699749946594,"standard_error":194.19429891722748},"slope":null,"std_dev":{"confidence_interval":{"confidence_level":0.95,"lower_bound":1899.4268256560981,"upper_bound":4702.659474079938},"point_estimate":3290.2286772409975,"standard_error":766.135124178459}}