{"mean":{"confidence_interval":{"confidence_level":0.95,"lower_bound":6515058.9209375,"upper_bound":6526199.2109687505},"point_estimate":6520120.06,"standard_error":2849.9802705613383},"median":{"confidence_interval":{"confidence_level":0.95,"lower_bound":6510336.5,"upper_bound":6513540.0},"point_estimate":6511906.4375,"standard_error":859.3334519381611},"median_abs_dev":{"confidence_interval":{"confidence_level":0.95,"lower_bound":4645.4490300267935,"upper_bound":8356.185956960528},"point_estimate":6416.044048592448,"standard_error":989.6731270712281},"slope":null,"std_dev":{"confidence_interval":{"confidence_level":0.95,"lower_bound":16288.09568178908,"upper_bound":38328.55208850185},"point_estimate":28548.11355855315,"standard_error":5720.9510317413315}}