{"mean":{"confidence_interval":{"confidence_level":0.95,"lower_bound":9215.020213272739,"upper_bound":9343.389758503257},"point_estimate":9271.162303323723,"standard_error":33.04619671479926},"median":{"confidence_interval":{"confidence_level":0.95,"lower_bound":9182.670027472528,"upper_bound":9263.358686257563},"point_estimate":9220.18132461331,"standard_error":20.208836630766676},"median_abs_dev":{"confidence_interval":{"confidence_level":0.95,"lower_bound":133.66725960918043,"upper_bound":221.52339535867068},"point_estimate":180.9210774537041,"standard_error":22.354764803303567},"slope":{"confidence_interval":{"confidence_level":0.95,"lower_bound":9177.722341689885,"upper_bound":9418.345808665612},"point_estimate":9266.52269179616,"standard_error":67.15828914974797},"std_dev":{"confidence_interval":{"confidence_level":0.95,"lower_bound":160.3504360664954,"upper_bound":504.7020440928684},"point_estimate":332.1517067723094,"standard_error":99.54395536966103}}