{"mean":{"confidence_interval":{"confidence_level":0.95,"lower_bound":7911131.877750003,"upper_bound":7934257.858214285},"point_estimate":7921317.332857141,"standard_error":5968.251388196562},"median":{"confidence_interval":{"confidence_level":0.95,"lower_bound":7904188.857142856,"upper_bound":7913938.428571429},"point_estimate":7908341.285714285,"standard_error":2804.9259519387833},"median_abs_dev":{"confidence_interval":{"confidence_level":0.95,"lower_bound":15641.059072316664,"upper_bound":29671.061473234247},"point_estimate":21444.43191928444,"standard_error":3720.063665590048},"slope":null,"std_dev":{"confidence_interval":{"confidence_level":0.95,"lower_bound":23231.897587187315,"upper_bound":88487.66437136946},"point_estimate":59999.21074088209,"standard_error":16665.036046774134}}