{"mean":{"confidence_interval":{"confidence_level":0.95,"lower_bound":98909122.528,"upper_bound":98954906.31475},"point_estimate":98931108.47,"standard_error":11684.796422328043},"median":{"confidence_interval":{"confidence_level":0.95,"lower_bound":98876400.0,"upper_bound":98916312.0},"point_estimate":98892312.5,"standard_error":10341.985790324708},"median_abs_dev":{"confidence_interval":{"confidence_level":0.95,"lower_bound":56270.59940099716,"upper_bound":109415.13675749302},"point_estimate":81436.25135421753,"standard_error":13854.252919396054},"slope":null,"std_dev":{"confidence_interval":{"confidence_level":0.95,"lower_bound":91289.14647646759,"upper_bound":140717.23975024343},"point_estimate":117127.64420847615,"standard_error":12649.116931509165}}