{"mean":{"confidence_interval":{"confidence_level":0.95,"lower_bound":6310.479960065197,"upper_bound":6371.046183685304},"point_estimate":6340.448491397163,"standard_error":15.421269013109535},"median":{"confidence_interval":{"confidence_level":0.95,"lower_bound":6266.94972826087,"upper_bound":6382.999761235955},"point_estimate":6307.887022243107,"standard_error":26.386321103671513},"median_abs_dev":{"confidence_interval":{"confidence_level":0.95,"lower_bound":141.6530761749141,"upper_bound":231.24577025354117},"point_estimate":196.97251050108443,"standard_error":23.60658046362488},"slope":{"confidence_interval":{"confidence_level":0.95,"lower_bound":6300.956297705168,"upper_bound":6371.564641311175},"point_estimate":6335.646295256392,"standard_error":18.07900857396423},"std_dev":{"confidence_interval":{"confidence_level":0.95,"lower_bound":139.38595703579722,"upper_bound":168.33020063456058},"point_estimate":154.7547214488709,"standard_error":7.393651633075153}}