{"mean":{"confidence_interval":{"confidence_level":0.95,"lower_bound":6512.431179346659,"upper_bound":6670.9407240925675},"point_estimate":6586.643939713653,"standard_error":40.41046653416309},"median":{"confidence_interval":{"confidence_level":0.95,"lower_bound":6404.814082740109,"upper_bound":6544.672727272728},"point_estimate":6477.133467023173,"standard_error":41.753680642438326},"median_abs_dev":{"confidence_interval":{"confidence_level":0.95,"lower_bound":164.9854007367714,"upper_bound":286.49588018688615},"point_estimate":222.92048693054778,"standard_error":32.32185187015358},"slope":{"confidence_interval":{"confidence_level":0.95,"lower_bound":6498.317881500817,"upper_bound":6631.603937518072},"point_estimate":6561.238507194003,"standard_error":34.016646705497486},"std_dev":{"confidence_interval":{"confidence_level":0.95,"lower_bound":268.4468599191069,"upper_bound":521.2107518048722},"point_estimate":406.9232828336133,"standard_error":64.49507013882234}}