{"mean":{"confidence_interval":{"confidence_level":0.95,"lower_bound":6439.1933648893655,"upper_bound":6486.9047746613705},"point_estimate":6463.465728745015,"standard_error":12.14032803196797},"median":{"confidence_interval":{"confidence_level":0.95,"lower_bound":6448.054044834308,"upper_bound":6498.854263565891},"point_estimate":6472.594,"standard_error":12.749056778545603},"median_abs_dev":{"confidence_interval":{"confidence_level":0.95,"lower_bound":66.58736937339263,"upper_bound":110.9834537223532},"point_estimate":84.30392623355011,"standard_error":11.151808312940215},"slope":{"confidence_interval":{"confidence_level":0.95,"lower_bound":6470.8737797968215,"upper_bound":6517.992848777437},"point_estimate":6495.909931530467,"standard_error":11.986858501949824},"std_dev":{"confidence_interval":{"confidence_level":0.95,"lower_bound":97.97613045276007,"upper_bound":142.75524868393495},"point_estimate":121.78319723583542,"standard_error":11.449965407154087}}